jcalc/__init__.py
jcalc/settings.py
jcalc/core/__init__.py
jcalc/core/md.py
jcalc/core/pdb.py
jcalc/logger/__init__.py
jcalc/logger/logger.py
jcalc-1.0.data/scripts/jcalc
jcalc-1.0.dist-info/LICENSE
jcalc-1.0.dist-info/METADATA
jcalc-1.0.dist-info/WHEEL
jcalc-1.0.dist-info/top_level.txt
jcalc-1.0.dist-info/RECORD
